pxutil/__init__.py
pxutil/__main__.py
pxutil/cli.py
pxutil/pxutil.py
pxutil/pxutil_cy.cpython-311-x86_64-linux-gnu.so
pxutil/pxutil_cy.py
tests/__init__.py
tests/manual_test_pxutil.py
tests/test_pxutil.py
pxutil-0.0.49.dist-info/METADATA
pxutil-0.0.49.dist-info/WHEEL
pxutil-0.0.49.dist-info/entry_points.txt
pxutil-0.0.49.dist-info/top_level.txt
pxutil-0.0.49.dist-info/RECORD
pxutil-0.0.49.dist-info/licenses/LICENSE
